betapert/__init__.py
betapert/funcs.py
beta_pert_dist_scipy-0.1.6.dist-info/METADATA
beta_pert_dist_scipy-0.1.6.dist-info/WHEEL
beta_pert_dist_scipy-0.1.6.dist-info/RECORD
