Metadata-Version: 2.3
Name: beta-pert-dist-scipy
Version: 0.1.6
Summary: Top-level package for beta-PERT distribution.
Author: Tom Adamczewski
Author-email: tadamczewskipublic@gmail.com
Requires-Python: >=3.11
Classifier: Natural Language :: English
Classifier: Programming Language :: Python :: 3
Classifier: Programming Language :: Python :: 3.11
Classifier: Programming Language :: Python :: 3.12
Classifier: Programming Language :: Python :: 3.13
Requires-Dist: scipy (>=1.14.0,<2.0.0)
Project-URL: Homepage, https://github.com/hbmartin/betapert
